django_query_to_table/DjangoQtt.py
django_query_to_table/__init__.py
django_query_to_table-1.1.1.dist-info/licenses/LICENSE.txt
django_query_to_table-1.1.1.dist-info/METADATA
django_query_to_table-1.1.1.dist-info/WHEEL
django_query_to_table-1.1.1.dist-info/top_level.txt
django_query_to_table-1.1.1.dist-info/RECORD
