Metadata-Version: 2.4
Name: django-query-to-table
Version: 1.1.1
Summary: A simple to use Django package to turn your queryset and sql query into a beautiful reporting html table
Home-page: https://github.com/birddevelper/django-query-to-table
Download-URL: https://pypi.org/project/django-query-to-table/
Author: R.E
License: GNU
Keywords: Django,Report,HTML,Table,SQL
License-File: LICENSE.txt
Requires-Dist: Django
Dynamic: author
Dynamic: description
Dynamic: description-content-type
Dynamic: download-url
Dynamic: home-page
Dynamic: keywords
Dynamic: license
Dynamic: license-file
Dynamic: requires-dist
Dynamic: summary
